{
  "id": "troubleshooting",
  "title": "Troubleshooting",
  "description": "Common Issues",
  "source": "@site/docs/troubleshooting.md",
  "sourceDirName": ".",
  "slug": "/troubleshooting",
  "permalink": "/dify_jira/docs/troubleshooting",
  "draft": false,
  "unlisted": false,
  "editUrl": "https://github.com/facebook/docusaurus/tree/main/packages/create-docusaurus/templates/shared/docs/troubleshooting.md",
  "tags": [],
  "version": "current",
  "sidebarPosition": 6,
  "frontMatter": {
    "sidebar_position": 6
  },
  "sidebar": "workshopSidebar",
  "previous": {
    "title": "Exercise 4: Advanced Prompting & Relevance Tuning",
    "permalink": "/dify_jira/docs/exercise-4-advanced-prompting"
  }
}